{
  "main": {
    "id": "6b28ace7a9d733be",
    "type": "split",
    "children": [
      {
        "id": "da62432a21262692",
        "type": "tabs",
        "children": [
          {
            "id": "12840bf219b40575",
            "type": "leaf",
            "state": {
              "type": "image",
              "state": {
                "file": "assets/images/20231009014939.png"
              }
            }
          }
        ]
      }
    ],
    "direction": "vertical"
  },
  "left": {
    "id": "477c8b273e0373ac",
    "type": "split",
    "children": [
      {
        "id": "036c1e0cc9348f5a",
        "type": "tabs",
        "children": [
          {
            "id": "4402694a62500985",
            "type": "leaf",
            "state": {
              "type": "file-explorer",
              "state": {
                "sortOrder": "alphabetical"
              }
            }
          },
          {
            "id": "0c507f49bd762b89",
            "type": "leaf",
            "state": {
              "type": "search",
              "state": {
                "query": "",
                "matchingCase": false,
                "explainSearch": false,
                "collapseAll": false,
                "extraContext": false,
                "sortOrder": "alphabetical"
              }
            }
          },
          {
            "id": "fd176b5e64b2c82b",
            "type": "leaf",
            "state": {
              "type": "bookmarks",
              "state": {}
            }
          }
        ]
      }
    ],
    "direction": "horizontal",
    "width": 300
  },
  "right": {
    "id": "60f0a433e367f8f1",
    "type": "split",
    "children": [
      {
        "id": "ee1d8b0947a64e07",
        "type": "tabs",
        "children": [
          {
            "id": "4e95c88348248fad",
            "type": "leaf",
            "state": {
              "type": "backlink",
              "state": {
                "file": "assets/images/20231009014939.png",
                "collapseAll": false,
                "extraContext": false,
                "sortOrder": "alphabetical",
                "showSearch": false,
                "searchQuery": "",
                "backlinkCollapsed": false,
                "unlinkedCollapsed": true
              }
            }
          },
          {
            "id": "2fd4845064e520e8",
            "type": "leaf",
            "state": {
              "type": "outgoing-link",
              "state": {
                "file": "assets/images/20231009014939.png",
                "linksCollapsed": false,
                "unlinkedCollapsed": true
              }
            }
          },
          {
            "id": "f45b16af234d1282",
            "type": "leaf",
            "state": {
              "type": "tag",
              "state": {
                "sortOrder": "frequency",
                "useHierarchy": true
              }
            }
          },
          {
            "id": "dc8e359a4c64a992",
            "type": "leaf",
            "state": {
              "type": "outline",
              "state": {
                "file": "assets/images/20231009014939.png"
              }
            }
          },
          {
            "id": "64d028e267c77c05",
            "type": "leaf",
            "state": {
              "type": "calendar",
              "state": {}
            }
          }
        ]
      }
    ],
    "direction": "horizontal",
    "width": 300
  },
  "left-ribbon": {
    "hiddenItems": {
      "switcher:Open quick switcher": false,
      "graph:Open graph view": false,
      "canvas:Create new canvas": false,
      "daily-notes:Open today's daily note": false,
      "templates:Insert template": false,
      "command-palette:Open command palette": false
    }
  },
  "active": "4402694a62500985",
  "lastOpenFiles": [
    "content/blog/Astro + Github Page setup blog cá nhân.md",
    "assets/images/20231009014939.png",
    "assets/images/image20231009014646.png",
    "assets/images/20231009at014533.png",
    "content/blog/adding-new-post.md",
    "assets/images/image20231009013855.png",
    "assets/images/Pasted image 20231009013717.png",
    "content/blog/astro-paper-3.md",
    "content/blog/astro-paper-2.md",
    "assets/images/Pastedimage20231009005827.png",
    "assets/images/Pasted image 20231009005827.png",
    "assets/images/Pasted image 20231009005731.png",
    "assets/images/Screenshot 2023-10-09 at 00.55.19.png",
    "assets/images/Pasted image 20231009005416.png",
    "content/blog/how-to-configure-astropaper-theme.md",
    "content/blog/customizing-astropaper-theme-color-schemes.md",
    "content/posts/2020-12-13-nhìn-lại-năm-2020-recap-2020.md",
    "content/posts/2020-12-09-tôi-đã-mất-tiền-ngu-từ-aws-như-thế-nào.md",
    "content/daily/09-10-2023.md",
    "Untitled.canvas",
    "content/blog/how-to-add-an-estimated-reading-time.md",
    "content/blog/example-draft-post.md",
    "content/blog/dynamic-og-images.md",
    "content/daily/08-10-2023.md",
    "content/daily",
    "content/journal/8-10-01-2021-vi-vu-đà-lạt.md",
    "content/notes/bắt-đầu-30daysproblemsolving.md",
    "content/pages/about.md"
  ]
}
